<?xml version="1.0" encoding="UTF-8"?>
<Defs>
    <SoundDef>
        <defName>NzRI_HurtSelf</defName>
        <context>MapOnly</context>
        <maxSimultaneous>1</maxSimultaneous>
        <priorityMode>PrioritizeNearest</priorityMode>
        <subSounds>
            <li>
                <grains>
                    <li Class="AudioGrain_Folder">
                        <clipFolderPath>HurtSelf</clipFolderPath>
                    </li>
                </grains>
                <volumeRange>40</volumeRange>
            </li>
        </subSounds>
    </SoundDef>

</Defs>