<?xml version="1.0" encoding="utf-8" ?>
<Defs>

	<!-- ====================== RimImmortal-Living update info ====================== -->

	<RI_Frame_Newspaper.UpdateNewsDef>
		<defName>RI_RimImmortal_Living_101</defName>
		<!-- Write translation key here, not the name directly -->
		<modName>RI_RimImmortal_Living</modName>
		<version>1.0.1</version>
		<!-- Write translation key here too -->
		<newsText>RI_RimImmortal_Living_Text</newsText>
		<imagePath>UI/News/News1</imagePath>
		<imageAspect>3.5</imageAspect>

		<!-- Fine-tune position and size here -->
		<windowX>8</windowX>
		<!-- Distance from screen left edge -->
		<windowY>510</windowY>
		<!-- Distance from screen top edge -->
		<windowWidth>500</windowWidth>
		<!-- Narrow the width slightly -->
		<windowHeight>277</windowHeight>
		<!-- Increase the height slightly -->
	</RI_Frame_Newspaper.UpdateNewsDef>

</Defs>